featureranker/__init__.py
featureranker/clustering.py
featureranker/plots.py
featureranker/rankers.py
featureranker/utils.py
featureranker-1.3.2.dist-info/LICENSE.md
featureranker-1.3.2.dist-info/METADATA
featureranker-1.3.2.dist-info/WHEEL
featureranker-1.3.2.dist-info/RECORD
