Metadata-Version: 2.3
Name: featureranker
Version: 1.3.2
Summary: Feature ranking ensemble
License: CC-BY-NC-SA-4.0
Keywords: feature, ranker, sklearn
Author: Logan Hallee
Author-email: lhallee99@gmail.com
Requires-Python: >=3.7,<4.0
Classifier: License :: Other/Proprietary License
Classifier: Programming Language :: Python :: 3
Classifier: Programming Language :: Python :: 3.7
Classifier: Programming Language :: Python :: 3.8
Classifier: Programming Language :: Python :: 3.9
Classifier: Programming Language :: Python :: 3.10
Classifier: Programming Language :: Python :: 3.11
Classifier: Programming Language :: Python :: 3.12
Classifier: Programming Language :: Python :: 3.13
Requires-Dist: matplotlib (>=3.8.1)
Requires-Dist: numpy (>=1.26.0)
Requires-Dist: pandas (>=2.1.1)
Requires-Dist: scikit-learn (>=1.3.2)
Requires-Dist: scikit-optimize (>=0.8.1)
Requires-Dist: scipy (>=1.11.2)
Requires-Dist: seaborn
Requires-Dist: tqdm (>=4.66.1)
Requires-Dist: xgboost (>=2.0.1)
Project-URL: Repository, https://github.com/lhallee/feature-ranker
